fedml_azure/__init__.py
fedml_azure/compute_creation.py
fedml_azure/dbconnection.py
fedml_azure/deployment.py
fedml_azure/dwc_azureml.py
fedml_azure/environment_creation.py
fedml_azure/install_validate.sh
fedml_azure/internal_config.json
fedml_azure/kyma_deploy.sh
fedml_azure/kyma_deployment.py
fedml_azure/logger.py
fedml_azure/resource_creation.py
fedml_azure/script_generator.py
fedml_azure/script_generator_helper.py
fedml_azure-2.0.1.data/scripts/install_validate.sh
fedml_azure-2.0.1.data/scripts/kyma_deploy.sh
fedml_azure-2.0.1.dist-info/LICENSE.txt
fedml_azure-2.0.1.dist-info/METADATA
fedml_azure-2.0.1.dist-info/WHEEL
fedml_azure-2.0.1.dist-info/top_level.txt
fedml_azure-2.0.1.dist-info/RECORD
