Metadata-Version: 2.1
Name: fedml-azure
Version: 2.0.1
Summary: A python library for building machine learning models on AzureML using a federated data source
Author: SAP SE
License: Apache License 2.0
Classifier: Programming Language :: Python :: 3
Classifier: Operating System :: OS Independent
Requires-Python: >=3
License-File: LICENSE.txt
Requires-Dist: hdbcli
Requires-Dist: ruamel.yaml
